idb/__init__.py
idb/analysis.py
idb/fileformat.py
idb/idapython.py
idb/netnode.py
idb/shim.py
idb/typeinf.py
idb/typeinf_flags.py
python_idb-0.8.0.dist-info/licenses/LICENSE.txt
python_idb-0.8.0.dist-info/METADATA
python_idb-0.8.0.dist-info/WHEEL
python_idb-0.8.0.dist-info/top_level.txt
python_idb-0.8.0.dist-info/RECORD
