Metadata-Version: 2.4
Name: python-idb
Version: 0.8.0
Summary: Pure Python parser for IDA Pro databases (.idb files)
Author-email: Willi Ballenthin <willi.ballenthin@gmail.com>
License-Expression: Apache-2.0
Project-URL: Homepage, https://github.com/williballenthin/python-idb
Classifier: Programming Language :: Python :: 3
Classifier: Programming Language :: Python :: 3.9
Classifier: Programming Language :: Python :: 3.10
Classifier: Programming Language :: Python :: 3.11
Classifier: Programming Language :: Python :: 3.12
Classifier: Programming Language :: Python :: 3.13
Classifier: Operating System :: OS Independent
Classifier: Topic :: Security
Classifier: Topic :: Software Development :: Disassemblers
Requires-Python: >=3.9
License-File: LICENSE.txt
Requires-Dist: six
Requires-Dist: hexdump>=3.3
Requires-Dist: vivisect-vstruct-wb>=1.0.3
Requires-Dist: cached-property>=1.5.1
Provides-Extra: disassembly
Requires-Dist: capstone>=5.0.6; extra == "disassembly"
Dynamic: license-file
